vbl_aquarium/__about__.py
vbl_aquarium/__init__.py
vbl_aquarium/build.py
vbl_aquarium/py.typed
vbl_aquarium/models/__init__.py
vbl_aquarium/models/dock.py
vbl_aquarium/models/ephys_link.py
vbl_aquarium/models/generic.py
vbl_aquarium/models/logging.py
vbl_aquarium/models/pinpoint.py
vbl_aquarium/models/proxy.py
vbl_aquarium/models/unity.py
vbl_aquarium/models/urchin.py
vbl_aquarium/utils/__init__.py
vbl_aquarium/utils/common.py
vbl_aquarium/utils/generate_csharp.py
vbl_aquarium/utils/vbl_base_model.py
vbl_aquarium-1.1.0.dist-info/METADATA
vbl_aquarium-1.1.0.dist-info/WHEEL
vbl_aquarium-1.1.0.dist-info/licenses/LICENSE
vbl_aquarium-1.1.0.dist-info/RECORD
