Metadata-Version: 2.4
Name: vbl-aquarium
Version: 1.1.0
Summary: Collection of Pydantic models describing data objects passed between Virtual Brain Lab projects.
Project-URL: Documentation, https://github.com/VirtualBrainLab/vbl-aquarium/blob/main/README.md
Project-URL: Issues, https://github.com/VirtualBrainLab/vbl-aquarium/issues
Project-URL: Source, https://github.com/VirtualBrainLab/vbl-aquarium
Author-email: Daniel Birman <dbirman@uw.edu>, Kenneth Yang <kjy5@uw.edu>
License-Expression: MIT
License-File: LICENSE
Keywords: neuroscience,pydantic,virtualbrainlab
Classifier: Development Status :: 4 - Beta
Classifier: Intended Audience :: Science/Research
Classifier: Operating System :: OS Independent
Classifier: Programming Language :: Python
Classifier: Programming Language :: Python :: 3
Classifier: Programming Language :: Python :: Implementation :: CPython
Classifier: Programming Language :: Python :: Implementation :: PyPy
Requires-Python: >=3.8
Requires-Dist: pydantic==2.12.3
